braingraphgeo
