Metadata-Version: 2.1
Name: braingraphgeo
Version: 0.2
Summary: Python package for performing analysis on structural brain networks using random geometric surrogate graphs
Home-page: https://github.com/scott-trinkle/braingraphgeo
Author: Scott Trinkle
Author-email: tscott.trinkle@gmail.com
License: MIT
Download-URL: https://github.com/scott-trinkle/braingraphgeo/archive/refs/tags/0.2.tar.gz
Keywords: tractography,brain network,graph theory
Platform: UNKNOWN
Classifier: Development Status :: 3 - Alpha
Classifier: Intended Audience :: Developers
Classifier: Topic :: Software Development :: Build Tools
Classifier: License :: OSI Approved :: MIT License
Classifier: Programming Language :: Python :: 3.7
Classifier: Programming Language :: Python :: 3.8
Classifier: Programming Language :: Python :: 3.9
